odoo/addons/l10n_es_aeat_mod390_oss/README.rst
odoo/addons/l10n_es_aeat_mod390_oss/__init__.py
odoo/addons/l10n_es_aeat_mod390_oss/__manifest__.py
odoo/addons/l10n_es_aeat_mod390_oss/data/tax_code_map_mod390_data.xml
odoo/addons/l10n_es_aeat_mod390_oss/i18n/es.po
odoo/addons/l10n_es_aeat_mod390_oss/i18n/l10n_es_aeat_mod390_oss.pot
odoo/addons/l10n_es_aeat_mod390_oss/models/__init__.py
odoo/addons/l10n_es_aeat_mod390_oss/models/mod390.py
odoo/addons/l10n_es_aeat_mod390_oss/readme/CONTRIBUTORS.rst
odoo/addons/l10n_es_aeat_mod390_oss/readme/DESCRIPTION.rst
odoo/addons/l10n_es_aeat_mod390_oss/readme/ROADMAP.rst
odoo/addons/l10n_es_aeat_mod390_oss/static/description/icon.png
odoo/addons/l10n_es_aeat_mod390_oss/static/description/icon.svg
odoo/addons/l10n_es_aeat_mod390_oss/static/description/index.html
odoo/addons/l10n_es_aeat_mod390_oss/tests/__init__.py
odoo/addons/l10n_es_aeat_mod390_oss/tests/test_l10n_es_aeat_mod390_oss.py
odoo14_addon_l10n_es_aeat_mod390_oss-14.0.1.0.1.dev5.dist-info/METADATA
odoo14_addon_l10n_es_aeat_mod390_oss-14.0.1.0.1.dev5.dist-info/WHEEL
odoo14_addon_l10n_es_aeat_mod390_oss-14.0.1.0.1.dev5.dist-info/top_level.txt
odoo14_addon_l10n_es_aeat_mod390_oss-14.0.1.0.1.dev5.dist-info/RECORD
